pelican_embed_svg/__init__.py
pelican_embed_svg/_embed_svg.py
pelican_embed_svg-0.0.3.dist-info/LICENSE
pelican_embed_svg-0.0.3.dist-info/METADATA
pelican_embed_svg-0.0.3.dist-info/WHEEL
pelican_embed_svg-0.0.3.dist-info/top_level.txt
pelican_embed_svg-0.0.3.dist-info/RECORD
